setup.py
Jyxml.egg-info/PKG-INFO
Jyxml.egg-info/SOURCES.txt
Jyxml.egg-info/dependency_links.txt
Jyxml.egg-info/requires.txt
Jyxml.egg-info/top_level.txt
jyxml/__init__.py
jyxml/exceptions.py
jyxml/json2xml.py
jyxml/json2yml.py