Metadata-Version: 1.2
Name: Jyxml
Version: 0.1.0
Summary: A simple python module for JSON - XML - YAML parsing.
Home-page: https://tbhaxor.github.io/jyxml
Author: Gurkirat Singh
Author-email: tbhaxor@gmail.com
License: GNU General Public License v3 (GPLv3)
Download-URL: https://github.com/tbhaxor/jyxml/archive/master.zip
Keywords: jyxml tbhaxor gurkirat singh
Platform: UNKNOWN
Classifier: Development Status :: 5 - Production/Stable
Classifier: Intended Audience :: Developers
Classifier: License :: OSI Approved :: GNU General Public License v3 (GPLv3)
Classifier: Programming Language :: Python :: 3
Classifier: Programming Language :: Python :: 3.2
Classifier: Programming Language :: Python :: 3.3
Classifier: Programming Language :: Python :: 3.4
Classifier: Programming Language :: Python :: 3.5
Classifier: Programming Language :: Python :: 3.6
Requires-Python: >=3
